cutil/__init__.py
cutil/config.py
cutil/custom_terminal.py
cutil/database.py
cutil/repeating_timer.py
cutil-3.0.3.dist-info/LICENSE
cutil-3.0.3.dist-info/METADATA
cutil-3.0.3.dist-info/WHEEL
cutil-3.0.3.dist-info/top_level.txt
cutil-3.0.3.dist-info/RECORD
