Metadata-Version: 2.1
Name: cutil
Version: 3.0.3
Summary: A collection of useful functions
Home-page: https://github.com/xtream1101/cutil
Author: Eddy Hintze
Author-email: eddy@hintze.co
License: MIT
Classifier: Programming Language :: Python :: 3
Classifier: Development Status :: 4 - Beta
Classifier: Environment :: Other Environment
Classifier: Operating System :: OS Independent
Classifier: Topic :: Software Development :: Libraries :: Python Modules
Classifier: Topic :: Utilities
License-File: LICENSE
Requires-Dist: hashids
Requires-Dist: pytz
Provides-Extra: postgres
Requires-Dist: psycopg2-binary ; extra == 'postgres'
